lhcbstyle/__init__.py
lhcbstyle/__main__.py
lhcbstyle/lhcbStyle.C
lhcbstyle/lhcbstyle.py
lhcbstyle-0.1.0.dist-info/COPYING
lhcbstyle-0.1.0.dist-info/METADATA
lhcbstyle-0.1.0.dist-info/WHEEL
lhcbstyle-0.1.0.dist-info/entry_points.txt
lhcbstyle-0.1.0.dist-info/top_level.txt
lhcbstyle-0.1.0.dist-info/zip-safe
lhcbstyle-0.1.0.dist-info/RECORD
