Metadata-Version: 2.1
Name: lhcbstyle
Version: 0.1.0
Summary: LHCb style for ROOT plots
Home-page: https://gitlab.cern.ch/lhcb-docs/lhcbstyle
Author: Adam Morris
Author-email: adam.morris@cern.ch
License: GPL-3.0-only
Platform: UNKNOWN
Classifier: Programming Language :: Python :: 3
Classifier: License :: OSI Approved :: GNU General Public License v3 (GPLv3)
Classifier: Operating System :: OS Independent
Requires-Python: >=3.7
Provides-Extra: testing
Requires-Dist: pytest ; extra == 'testing'
Requires-Dist: pytest-cov ; extra == 'testing'
Requires-Dist: pre-commit ; extra == 'testing'
